ordeq_pydantic/__init__.py
ordeq_pydantic/_version.py
ordeq_pydantic/json.py
ordeq_pydantic/model.py
ordeq_pydantic/py.typed
ordeq_pydantic-1.0.2.dist-info/licenses/LICENSE
ordeq_pydantic-1.0.2.dist-info/METADATA
ordeq_pydantic-1.0.2.dist-info/WHEEL
ordeq_pydantic-1.0.2.dist-info/top_level.txt
ordeq_pydantic-1.0.2.dist-info/RECORD
